[
    {
      "parentId": 0,
      "name": "ANDHRA PRADESH",
      "abbreviation": "AP",
      "alternateAbbreviation": "IN-AP",
      "code": 37,
      "isdeleted": false,
      "insertedBy": 1,
      "insertedDate": "2020-10-14T13:23:14.1525512",
      "updatedBy": 0,
      "updatedDate": null,
      "deletedBy": 0,
      "deletedDate": null
    },
    {
      "parentId": 0,
      "name": "ARUNACHAL PRADESH",
      "abbreviation": "AR",
      "alternateAbbreviation": "IN-AR",
      "code": 12,
      "isdeleted": false,
      "insertedBy": 1,
      "insertedDate": "2020-10-14T13:23:14.1525512",
      "updatedBy": 0,
      "updatedDate": null,
      "deletedBy": 0,
      "deletedDate": null
    },
    {
      "parentId": 0,
      "name": "ASSAM",
      "abbreviation": "AS",
      "alternateAbbreviation": "IN-AS",
      "code": 18,
      "isdeleted": false,
      "insertedBy": 1,
      "insertedDate": "2020-10-14T13:23:54.6922656",
      "updatedBy": 0,
      "updatedDate": null,
      "deletedBy": 0,
      "deletedDate": null
    },
    {
      "parentId": 0,
      "name": "BIHAR",
      "abbreviation": "BR",
      "alternateAbbreviation": "IN-BR",
      "code": 10,
      "isdeleted": false,
      "insertedBy": 1,
      "insertedDate": "2020-10-14T13:24:43.0210105",
      "updatedBy": 0,
      "updatedDate": null,
      "deletedBy": 0,
      "deletedDate": null
    },
    {
      "parentId": 0,
      "name": "CHHATTISGARH",
      "abbreviation": "CG",
      "alternateAbbreviation": "IN-CG",
      "code": 22,
      "isdeleted": false,
      "insertedBy": 1,
      "insertedDate": "2020-10-14T13:25:27.3002596",
      "updatedBy": 0,
      "updatedDate": null,
      "deletedBy": 0,
      "deletedDate": null
    },
    {
      "parentId": 0,
      "name": "GOA",
      "abbreviation": "GA",
      "alternateAbbreviation": "IN-GA",
      "code": 30,
      "isdeleted": false,
      "insertedBy": 1,
      "insertedDate": "2020-10-14T13:26:05.3365357",
      "updatedBy": 0,
      "updatedDate": null,
      "deletedBy": 0,
      "deletedDate": null
    },
    {
      "parentId": 0,
      "name": "GUJARAT",
      "abbreviation": "GJ",
      "alternateAbbreviation": "IN-GJ",
      "code": 24,
      "isdeleted": false,
      "insertedBy": 1,
      "insertedDate": "2020-10-14T13:26:49.6934184",
      "updatedBy": 0,
      "updatedDate": null,
      "deletedBy": 0,
      "deletedDate": null
    },
    {
      "parentId": 0,
      "name": "HARYANA",
      "abbreviation": "HR",
      "alternateAbbreviation": "IN-HR",
      "code": 6,
      "isdeleted": false,
      "insertedBy": 1,
      "insertedDate": "2020-10-14T13:27:44.4894526",
      "updatedBy": 0,
      "updatedDate": null,
      "deletedBy": 0,
      "deletedDate": null
    },
    {
      "parentId": 0,
      "name": "HIMACHAL PRADESH",
      "abbreviation": "HP",
      "alternateAbbreviation": "IN-HP",
      "code": 2,
      "isdeleted": false,
      "insertedBy": 1,
      "insertedDate": "2020-10-14T13:28:20.8465946",
      "updatedBy": 0,
      "updatedDate": null,
      "deletedBy": 0,
      "deletedDate": null
    },
    {
      "parentId": 0,
      "name": "JAMMU AND KASHMIR",
      "abbreviation": "JK",
      "alternateAbbreviation": "IN-JK",
      "code": 1,
      "isdeleted": false,
      "insertedBy": 1,
      "insertedDate": "2020-10-14T13:28:51.6097679",
      "updatedBy": 0,
      "updatedDate": null,
      "deletedBy": 0,
      "deletedDate": null
    },
    {
      "parentId": 0,
      "name": "JHARKHAND",
      "abbreviation": "JH",
      "alternateAbbreviation": "IN-JH",
      "code": 20,
      "isdeleted": false,
      "insertedBy": 1,
      "insertedDate": "2020-10-14T13:29:29.5994363",
      "updatedBy": 0,
      "updatedDate": null,
      "deletedBy": 0,
      "deletedDate": null
    },
    {
      "parentId": 0,
      "name": "KARNATAKA",
      "abbreviation": "KA",
      "alternateAbbreviation": "IN-KA",
      "code": 29,
      "isdeleted": false,
      "insertedBy": 1,
      "insertedDate": "2020-10-14T13:30:21.812125",
      "updatedBy": 0,
      "updatedDate": null,
      "deletedBy": 0,
      "deletedDate": null
    },
    {
      "parentId": 0,
      "name": "KERALA",
      "abbreviation": "KL",
      "alternateAbbreviation": "IN-KL",
      "code": 32,
      "isdeleted": false,
      "insertedBy": 1,
      "insertedDate": "2020-10-14T13:31:26.3176476",
      "updatedBy": 0,
      "updatedDate": null,
      "deletedBy": 0,
      "deletedDate": null
    },
    {
      "parentId": 0,
      "name": "MADHYA PRADESH",
      "abbreviation": "MP",
      "alternateAbbreviation": "IN-MP",
      "code": 23,
      "isdeleted": false,
      "insertedBy": 1,
      "insertedDate": "2020-10-14T13:32:10.316397",
      "updatedBy": 0,
      "updatedDate": null,
      "deletedBy": 0,
      "deletedDate": null
    },
    {
      "parentId": 0,
      "name": "MAHARASHTRA",
      "abbreviation": "MH",
      "alternateAbbreviation": "IN-MH",
      "code": 27,
      "isdeleted": false,
      "insertedBy": 1,
      "insertedDate": "2020-10-14T13:33:18.5924826",
      "updatedBy": 0,
      "updatedDate": null,
      "deletedBy": 0,
      "deletedDate": null
    },
    {
      "parentId": 0,
      "name": "MANIPUR",
      "abbreviation": "MN",
      "alternateAbbreviation": "IN-MN",
      "code": 14,
      "isdeleted": false,
      "insertedBy": 1,
      "insertedDate": "2020-10-14T13:33:52.2741914",
      "updatedBy": 0,
      "updatedDate": null,
      "deletedBy": 0,
      "deletedDate": null
    },
    {
      "parentId": 0,
      "name": "MEGHALAYA",
      "abbreviation": "ML",
      "alternateAbbreviation": "IN-ML",
      "code": 17,
      "isdeleted": false,
      "insertedBy": 1,
      "insertedDate": "2020-10-14T13:35:45.4868584",
      "updatedBy": 0,
      "updatedDate": null,
      "deletedBy": 0,
      "deletedDate": null
    },
    {
      "parentId": 0,
      "name": "MIZORAM",
      "abbreviation": "MZ",
      "alternateAbbreviation": "IN-MZ",
      "code": 15,
      "isdeleted": false,
      "insertedBy": 1,
      "insertedDate": "2020-10-14T13:36:17.1192041",
      "updatedBy": 0,
      "updatedDate": null,
      "deletedBy": 0,
      "deletedDate": null
    },
    {
      "parentId": 0,
      "name": "NAGALAND",
      "abbreviation": "NL",
      "alternateAbbreviation": "IN-NL",
      "code": 13,
      "isdeleted": false,
      "insertedBy": 1,
      "insertedDate": "2020-10-14T13:37:02.6659113",
      "updatedBy": 0,
      "updatedDate": null,
      "deletedBy": 0,
      "deletedDate": null
    },
    {
      "parentId": 0,
      "name": "ORISSA",
      "abbreviation": "OR",
      "alternateAbbreviation": "IN-OR",
      "code": 21,
      "isdeleted": false,
      "insertedBy": 1,
      "insertedDate": "2020-10-14T13:37:37.6724762",
      "updatedBy": 0,
      "updatedDate": null,
      "deletedBy": 0,
      "deletedDate": null
    },
    {
      "id": 21,
      "parentId": 0,
      "name": "PUNJAB",
      "abbreviation": "PB",
      "alternateAbbreviation": "IN-PB",
      "code": 3,
      "isdeleted": false,
      "insertedBy": 1,
      "insertedDate": "2020-10-14T13:38:04.5819966",
      "updatedBy": 0,
      "updatedDate": null,
      "deletedBy": 0,
      "deletedDate": null
    },
    {
      "parentId": 0,
      "name": "RAJASTHAN",
      "abbreviation": "RJ",
      "alternateAbbreviation": "IN-RJ",
      "code": 8,
      "isdeleted": false,
      "insertedBy": 1,
      "insertedDate": "2020-10-14T13:38:50.7758311",
      "updatedBy": 0,
      "updatedDate": null,
      "deletedBy": 0,
      "deletedDate": null
    },
    {
      "parentId": 0,
      "name": "SIKKIM",
      "abbreviation": "SK",
      "alternateAbbreviation": "IN-RJ",
      "code": 11,
      "isdeleted": false,
      "insertedBy": 1,
      "insertedDate": "2020-10-14T13:39:18.3904718",
      "updatedBy": 0,
      "updatedDate": null,
      "deletedBy": 0,
      "deletedDate": null
    },
    {
      "parentId": 0,
      "name": "TAMIL NADU",
      "abbreviation": "TN",
      "alternateAbbreviation": "IN-TN",
      "code": 33,
      "isdeleted": false,
      "insertedBy": 1,
      "insertedDate": "2020-10-14T13:39:58.2237857",
      "updatedBy": 0,
      "updatedDate": null,
      "deletedBy": 0,
      "deletedDate": null
    },
    {
      "parentId": 0,
      "name": "TRIPURA",
      "abbreviation": "TR",
      "alternateAbbreviation": "IN-TR",
      "code": 16,
      "isdeleted": false,
      "insertedBy": 1,
      "insertedDate": "2020-10-14T13:40:25.8024632",
      "updatedBy": 0,
      "updatedDate": null,
      "deletedBy": 0,
      "deletedDate": null
    },
    {
      "parentId": 0,
      "name": "UTTARAKHAND",
      "abbreviation": "UK",
      "alternateAbbreviation": "IN-UK",
      "code": 5,
      "isdeleted": false,
      "insertedBy": 1,
      "insertedDate": "2020-10-14T13:41:03.1581177",
      "updatedBy": 0,
      "updatedDate": null,
      "deletedBy": 0,
      "deletedDate": null
    },
    {
      "parentId": 0,
      "name": "UTTAR PRADESH",
      "abbreviation": "UP",
      "alternateAbbreviation": "IN-UP",
      "code": 9,
      "isdeleted": false,
      "insertedBy": 1,
      "insertedDate": "2020-10-14T13:41:35.9833416",
      "updatedBy": 0,
      "updatedDate": null,
      "deletedBy": 0,
      "deletedDate": null
    },
    {
      "parentId": 0,
      "name": "WEST BENGAL",
      "abbreviation": "WB",
      "alternateAbbreviation": "IN-WB",
      "code": 19,
      "isdeleted": false,
      "insertedBy": 1,
      "insertedDate": "2020-10-14T13:42:11.2072501",
      "updatedBy": 0,
      "updatedDate": null,
      "deletedBy": 0,
      "deletedDate": null
    },
    {
      "parentId": 0,
      "name": "ANDAMAN AND NICOBAR ISLANDS",
      "abbreviation": "AN",
      "alternateAbbreviation": "IN-AN",
      "code": 35,
      "isdeleted": false,
      "insertedBy": 1,
      "insertedDate": "2020-10-14T13:45:04.0337816",
      "updatedBy": 0,
      "updatedDate": null,
      "deletedBy": 0,
      "deletedDate": null
    },
    {
      "parentId": 0,
      "name": "CHANDIGARH",
      "abbreviation": "CH",
      "alternateAbbreviation": "IN-CH",
      "code": 4,
      "isdeleted": false,
      "insertedBy": 1,
      "insertedDate": "2020-10-14T13:45:50.8311054",
      "updatedBy": 0,
      "updatedDate": null,
      "deletedBy": 0,
      "deletedDate": null
    },
    {
      "parentId": 0,
      "name": "DADRA AND NAGAR HAVELI",
      "abbreviation": "DH",
      "alternateAbbreviation": "IN-DH",
      "code": 26,
      "isdeleted": false,
      "insertedBy": 1,
      "insertedDate": "2020-10-14T13:46:16.9725483",
      "updatedBy": 0,
      "updatedDate": null,
      "deletedBy": 0,
      "deletedDate": null
    },
    {
      "parentId": 0,
      "name": "DAMAN AND DIU",
      "abbreviation": "DD",
      "alternateAbbreviation": "IN-DD",
      "code": 25,
      "isdeleted": false,
      "insertedBy": 1,
      "insertedDate": "2020-10-14T13:46:55.9415598",
      "updatedBy": 0,
      "updatedDate": null,
      "deletedBy": 0,
      "deletedDate": null
    },
    {
      "parentId": 0,
      "name": "DELHI",
      "abbreviation": "DL",
      "alternateAbbreviation": "IN-DL",
      "code": 7,
      "isdeleted": false,
      "insertedBy": 1,
      "insertedDate": "2020-10-14T13:47:24.4317625",
      "updatedBy": 0,
      "updatedDate": null,
      "deletedBy": 0,
      "deletedDate": null
    },
    {
      "parentId": 0,
      "name": "LAKSHADWEEP",
      "abbreviation": "LD",
      "alternateAbbreviation": "IN-LD",
      "code": 31,
      "isdeleted": false,
      "insertedBy": 1,
      "insertedDate": "2020-10-14T13:48:04.9836999",
      "updatedBy": 0,
      "updatedDate": null,
      "deletedBy": 0,
      "deletedDate": null
    },
    {
      "parentId": 0,
      "name": "PONDICHERRY",
      "abbreviation": "PY",
      "alternateAbbreviation": "IN-PY",
      "code": 34,
      "isdeleted": false,
      "insertedBy": 1,
      "insertedDate": "2020-10-14T13:49:42.8146996",
      "updatedBy": 0,
      "updatedDate": null,
      "deletedBy": 0,
      "deletedDate": null
    },
    {
      "parentId": 0,
      "name": "JABALPUR",
      "abbreviation": "JBPL",
      "alternateAbbreviation": "",
      "code": 34,
      "isdeleted": false,
      "insertedBy": 1,
      "insertedDate": "2020-10-14T13:49:42.8146996",
      "updatedBy": 0,
      "updatedDate": null,
      "deletedBy": 0,
      "deletedDate": null
    }
  ]